LICENSE.txt
MANIFEST.in
README.md
setup.py
test.py
intersection/__init__.py
intersection/comment.py
intersection/highscore.py
intersection/map.py
intersection/user.py
intersection.py.egg-info/PKG-INFO
intersection.py.egg-info/SOURCES.txt
intersection.py.egg-info/dependency_links.txt
intersection.py.egg-info/requires.txt
intersection.py.egg-info/top_level.txt
intersection/ext/__init__.py
intersection/ext/url.py