Metadata-Version: 2.1
Name: intersection.py
Version: 2.0.1
Summary: A simple API Wrapper for IC
Home-page: https://github.com/Feeeeddmmmeee/intersection.py
Author: Feeeeddmmmeee
Author-email: 
License: MIT
Keywords: api
Platform: UNKNOWN
Classifier: Development Status :: 5 - Production/Stable
Classifier: Intended Audience :: Developers
Classifier: Operating System :: Microsoft :: Windows :: Windows 10
Classifier: License :: OSI Approved :: MIT License
Classifier: Programming Language :: Python :: 3
License-File: LICENSE.txt
